flet_mvc/__init__.py
flet_mvc/alert.py
flet_mvc/controller.py
flet_mvc/model.py
flet_mvc/routing.py
flet_mvc/view.py
mvc_commands/__init__.py
mvc_commands/cli.py
mvc_commands/templates/basic/app.py
mvc_commands/templates/basic/controllers/main.py
mvc_commands/templates/basic/models/main.py
mvc_commands/templates/basic/views/main.py
mvc_commands/templates/routes/app.py
mvc_commands/templates/routes/controllers/home.py
mvc_commands/templates/routes/controllers/secundary.py
mvc_commands/templates/routes/models/home.py
mvc_commands/templates/routes/models/secundary.py
mvc_commands/templates/routes/views/home.py
mvc_commands/templates/routes/views/secundary.py
mvc_commands/templates/tabs/app.py
mvc_commands/templates/tabs/controllers/home.py
mvc_commands/templates/tabs/controllers/index.py
mvc_commands/templates/tabs/controllers/settings.py
mvc_commands/templates/tabs/models/home.py
mvc_commands/templates/tabs/models/index.py
mvc_commands/templates/tabs/models/settings.py
mvc_commands/templates/tabs/views/home.py
mvc_commands/templates/tabs/views/index.py
mvc_commands/templates/tabs/views/settings.py
flet_mvc-0.1.5.dist-info/LICENSE
flet_mvc-0.1.5.dist-info/METADATA
flet_mvc-0.1.5.dist-info/WHEEL
flet_mvc-0.1.5.dist-info/entry_points.txt
flet_mvc-0.1.5.dist-info/top_level.txt
flet_mvc-0.1.5.dist-info/RECORD
